[
  {
    "full_name": "juce-framework/JUCE",
    "stargazers_count": 4297,
    "open_issues_count": 263,
    "forks_count": 1279
  },
  {
    "full_name": "sudheerj/vuejs-interview-questions",
    "stargazers_count": 1654,
    "open_issues_count": 1,
    "forks_count": 455
  },
  {
    "full_name": "dabit3/nuxt-supabase-full-multi-user-blog",
    "stargazers_count": 54,
    "open_issues_count": 1,
    "forks_count": 8
  },
  {
    "full_name": "nuxt/create-nuxt-app",
    "stargazers_count": 3239,
    "open_issues_count": 127,
    "forks_count": 423
  },
  {
    "full_name": "supabase/supabase",
    "stargazers_count": 34927,
    "open_issues_count": 272,
    "forks_count": 2089
  },
  {
    "full_name": "onderceylan/pwa-asset-generator",
    "stargazers_count": 2046,
    "open_issues_count": 37,
    "forks_count": 107
  },
  {
    "full_name": "cosmicjs/vue-music-website",
    "stargazers_count": 90,
    "open_issues_count": 2,
    "forks_count": 21
  },
  {
    "full_name": "slidenerd/nuxt-auth",
    "stargazers_count": 3,
    "open_issues_count": 1,
    "forks_count": 0
  },
  {
    "full_name": "vuejs/awesome-vue",
    "stargazers_count": 65552,
    "open_issues_count": 35,
    "forks_count": 9052
  },
  {
    "full_name": "ivodolenc/nuxt-animejs",
    "stargazers_count": 58,
    "open_issues_count": 0,
    "forks_count": 1
  },
  {
    "full_name": "iina/iina",
    "stargazers_count": 30478,
    "open_issues_count": 1355,
    "forks_count": 2292
  },
  {
    "full_name": "imadovitch/Horizontal-Animation-on-Vertical-Scroll-using-Vue.js-TailwindCSS",
    "stargazers_count": 5,
    "open_issues_count": 0,
    "forks_count": 2
  },
  {
    "full_name": "imadovitch/Music-Player-App-built-with-Vue.js-Vue3-and-Howler.js",
    "stargazers_count": 39,
    "open_issues_count": 0,
    "forks_count": 15
  },
  {
    "full_name": "Asabeneh/JavaScript-for-Everyone",
    "stargazers_count": 567,
    "open_issues_count": 0,
    "forks_count": 205
  },
  {
    "full_name": "Asabeneh/30-Days-Of-JavaScript",
    "stargazers_count": 24236,
    "open_issues_count": 57,
    "forks_count": 5241
  },
  {
    "full_name": "rogden/tailwind-config-viewer",
    "stargazers_count": 1380,
    "open_issues_count": 25,
    "forks_count": 68
  },
  {
    "full_name": "kehers/paystack",
    "stargazers_count": 114,
    "open_issues_count": 11,
    "forks_count": 67
  },
  {
    "full_name": "sindresorhus/awesome",
    "stargazers_count": 207043,
    "open_issues_count": 38,
    "forks_count": 23675
  },
  {
    "full_name": "acekyd/made-in-nigeria",
    "stargazers_count": 766,
    "open_issues_count": 5,
    "forks_count": 348
  },
  {
    "full_name": "MunGell/awesome-for-beginners",
    "stargazers_count": 41218,
    "open_issues_count": 92,
    "forks_count": 5682
  },
  {
    "full_name": "thembari/API",
    "stargazers_count": 2,
    "open_issues_count": 0,
    "forks_count": 0
  },
  {
    "full_name": "bdelate/django-flutterwave",
    "stargazers_count": 18,
    "open_issues_count": 0,
    "forks_count": 7
  },
  {
    "full_name": "nesdis/djongo",
    "stargazers_count": 1571,
    "open_issues_count": 297,
    "forks_count": 286
  },
  {
    "full_name": "Maduflavins/paystackimplementation",
    "stargazers_count": 1,
    "open_issues_count": 0,
    "forks_count": 0
  },
  {
    "full_name": "Olamidun/pricetrackerapi",
    "stargazers_count": 1,
    "open_issues_count": 0,
    "forks_count": 0
  },
  {
    "full_name": "public-apis/public-apis",
    "stargazers_count": 198719,
    "open_issues_count": 24,
    "forks_count": 22871
  },
  {
    "full_name": "sithis993/Crypter",
    "stargazers_count": 435,
    "open_issues_count": 16,
    "forks_count": 166
  },
  {
    "full_name": "Gloryness/Multiprocessing-in-PyQt5",
    "stargazers_count": 4,
    "open_issues_count": 0,
    "forks_count": 1
  },
  {
    "full_name": "EbookFoundation/free-programming-books",
    "stargazers_count": 237786,
    "open_issues_count": 39,
    "forks_count": 49372
  },
  {
    "full_name": "maxogden/art-of-node",
    "stargazers_count": 9439,
    "open_issues_count": 17,
    "forks_count": 893
  }
]